ioform/__init__.py
ioform/ioform.py
ioform/dist/favicon.ico
ioform/dist/index.html
ioform/dist/css/app.7dfe7e3e.css
ioform/dist/css/chunk-vendors.454776ae.css
ioform/dist/js/app.78585af7.js
ioform/dist/js/app.78585af7.js.map
ioform/dist/js/chunk-vendors.4779498b.js
ioform/dist/js/chunk-vendors.4779498b.js.map
ioform-0.0.20.dist-info/LICENSE
ioform-0.0.20.dist-info/METADATA
ioform-0.0.20.dist-info/WHEEL
ioform-0.0.20.dist-info/top_level.txt
ioform-0.0.20.dist-info/RECORD
