Metadata-Version: 2.1
Name: ioform
Version: 0.0.20
Summary: Input Output Web Form
Home-page: https://github.com/ucipass/frontent
Author: ucipass
Author-email: ucipass@gmail.com
License: UNKNOWN
Project-URL: Bug Tracker, https://github.com/pypa/sampleproject/issues
Platform: UNKNOWN
Classifier: Programming Language :: Python :: 3
Classifier: License :: OSI Approved :: MIT License
Classifier: Operating System :: OS Independent
Requires-Python: >=3.6
License-File: LICENSE
Requires-Dist: tornado
Requires-Dist: python-socketio
Requires-Dist: pyyaml
Requires-Dist: cryptography (<4.0.0,>=3.3.1)
